appmath/__init__.py
appmath/optimization/__init__.py
appmath/optimization/uniform.py
appmath/optimization/unconditional/__init__.py
appmath/optimization/unconditional/zeroorder/__init__.py
appmath/optimization/unconditional/zeroorder/onedimensional/__init__.py
appmath/optimization/unconditional/zeroorder/onedimensional/base_method.py
appmath/optimization/unconditional/zeroorder/onedimensional/dichotomy.py
appmath/optimization/unconditional/zeroorder/onedimensional/divhalf.py
appmath/optimization/unconditional/zeroorder/onedimensional/fibbonachi.py
appmath/optimization/unconditional/zeroorder/onedimensional/golden_ratio.py
appmath/optimization/unconditional/zeroorder/onedimensional/uniform.py
appmath-0.0.1.17.dist-info/METADATA
appmath-0.0.1.17.dist-info/WHEEL
appmath-0.0.1.17.dist-info/top_level.txt
appmath-0.0.1.17.dist-info/RECORD
