Metadata-Version: 2.1
Name: appmath
Version: 0.0.1.17
Summary: Some methods of numerical mathematics which support calculation on GPU and parallelization
Home-page: https://github.com/aogavrilov/appmath
Author: Alexey Gavrilov
Author-email: alexgavrilov28@gmail.com
License: MIT
Keywords: GPU
Platform: any
Classifier: Development Status :: 3 - Alpha
Classifier: Intended Audience :: Developers
Classifier: License :: OSI Approved :: MIT License
Classifier: Operating System :: OS Independent
Classifier: Programming Language :: Python
Classifier: Programming Language :: Python :: 3.4
Classifier: Programming Language :: Python :: 3.5
Classifier: Programming Language :: Python :: 3.6
Classifier: Programming Language :: Python :: 3.7
Classifier: Programming Language :: Python :: 3.8
Classifier: Topic :: Software Development :: Libraries :: Python Modules
Requires-Python: !=3.0.*,!=3.1.*,!=3.2.*,>=2.7
